src/design/module_led.sv
module module_led(
    input logic [3:0] in,
    output logic [3:0] out
);

    // Asignación de los LEDs a los bits de entrada
    assign out[0] = ~in[0]; // LED 0
    assign out[1] = ~in[1]; // LED 1
    assign out[2] = ~in[2]; // LED 2
    assign out[3] = ~in[3]; // LED 3

    // Se puede agregar lógica adicional aquí si es necesario
    // para controlar el comportamiento de los LEDs.
    // Por ejemplo, invertir la señal de un LED:
    // assign out[0] = ~in[0]; // Invertir LED 0
endmodule

src/sim/module_led_tb.sv
`timescale 1ns/1ns

module module_led_tb;

    // Definición de las señales de prueba
    reg [3:0] led_in; // Entrada de 4 bits
    wire [3:0] led_out; // Salida de 4 bits

    // Instancia del módulo a probar
    module_led dut (
        .in(led_in),
        .out(led_out)
    );

// Generación de estímulos
    initial begin
        $display("-------|---------|--------");
        $display("Tiempo | Entrada | Salida ");
        $display("-------|---------|--------");

        // Monitoreo de las señales
        $monitor("Tiempo = %t, Entrada = %b, Salida = %b", $time , led_in, led_out);
    
        // Estímulos de prueba
        led_in = 4'b0000; #10; // Caso 0
        led_in = 4'b0001; #10; // Caso 1
        led_in = 4'b0010; #10; // Caso 2
        led_in = 4'b0011; #10; // Caso 3
        led_in = 4'b0100; #10; // Caso 4
        led_in = 4'b0101; #10; // Caso 5
        led_in = 4'b0110; #10; // Caso 6
        led_in = 4'b0111; #10; // Caso 7
        led_in = 4'b1000; #10; // Caso 8
        led_in = 4'b1001; #10; // Caso 9
        led_in = 4'b1010; #10; // Caso A
        led_in = 4'b1011; #10; // Caso B
        led_in = 4'b1100; #10; // Caso C
        led_in = 4'b1101; #10; // Caso D
        led_in = 4'b1110; #10; // Caso E
        led_in = 4'b1111; #10; // Caso F
    end 

    initial begin
        $dumpfile("module_led_tb.vcd");
        $dumpvars(0, module_led_tb);
    end
endmodule

src/build/module_led_tb.vcd
$date
	Wed Apr 02 16:02:26 2025
$end
$version
	Icarus Verilog
$end
$timescale
	1ns
$end
$scope module module_led_tb $end
$var wire 4 ! led_out [3:0] $end
$var reg 4 " led_in [3:0] $end
$scope module dut $end
$var wire 4 # in [3:0] $end
$var wire 4 $ out [3:0] $end
$upscope $end
$upscope $end
$enddefinitions $end
$comment Show the parameter values. $end
$dumpall
$end
#0
$dumpvars
b1111 $
b0 #
b0 "
b1111 !
$end
#10
b1110 !
b1110 $
b1 "
b1 #
#20
b1101 !
b1101 $
b10 "
b10 #
#30
b1100 !
b1100 $
b11 "
b11 #
#40
b1011 !
b1011 $
b100 "
b100 #
#50
b1010 !
b1010 $
b101 "
b101 #
#60
b1001 !
b1001 $
b110 "
b110 #
#70
b1000 !
b1000 $
b111 "
b111 #
#80
b111 !
b111 $
b1000 "
b1000 #
#90
b110 !
b110 $
b1001 "
b1001 #
#100
b101 !
b101 $
b1010 "
b1010 #
#110
b100 !
b100 $
b1011 "
b1011 #
#120
b11 !
b11 $
b1100 "
b1100 #
#130
b10 !
b10 $
b1101 "
b1101 #
#140
b1 !
b1 $
b1110 "
b1110 #
#150
b0 !
b0 $
b1111 "
b1111 #
