src/design/module_errordisp.sv
module module_errordisp(
    input logic bit_error,
    output logic[6:0] disp_error
);
    // Asignación del error al display de 7 segmentos
    assign disp_error = (bit_error == 1'b1) ? 7'b011_0000 :
                        (bit_error == 1'b0) ? 7'b111_1110 :
                        7'bxxx_xxxx;
endmodule

src/design/module_led.sv
module module_led(
    input logic [3:0] in,
    output logic [3:0] out
);

    // Asignación de los LEDs a los bits de entrada
    assign out[0] = ~in[0]; // LED 0
    assign out[1] = ~in[1]; // LED 1
    assign out[2] = ~in[2]; // LED 2
    assign out[3] = ~in[3]; // LED 3

    // Se puede agregar lógica adicional aquí si es necesario
    // para controlar el comportamiento de los LEDs.
    // Por ejemplo, invertir la señal de un LED:
    // assign out[0] = ~in[0]; // Invertir LED 0
endmodule

src/design/module_decodificador.sv
module module_decodificador ( // Modulo decodificador de una palabra de 7 bits. Segunda parte del código de hamming 3
    input logic [6:0] datos_cod,     //Entrada de 7 bits [i3,i2,i1,c2,i0,c1,c0]
    output logic [3:0] datos_out      //Salida de 4 bits [i3,i2,i1,i0]
); 

assign datos_out[0] = datos_cod[2]; // i0
assign datos_out[1] = datos_cod[4]; // i1
assign datos_out[2] = datos_cod[5]; // i2
assign datos_out[3] = datos_cod[6]; // i3

endmodule

src/design/module_corrector_error.sv
module module_corrector_error(
    input  logic[2:0] sindrome,        // Entrada de 3 bits [p2,p1,p0]. Síndrome de error.
    input  logic[6:0] datos_recibidos,  // Entrada de 7 bits [i3,i2,i1,c2,i0,c1,c0].
    output logic[6:0] data             // Salida de 7 bits [i3,i2,i1,c2,i0,c1,c0].  
);
// Decodificador 3 a 8 de 8bits.                     // Valores para guardar posicion de bit erroneo.
// logic [7:0] data8;   
 
// assign data8[7] = &{~sindrome[0], ~sindrome[1], ~sindrome[2]};     // Valor si el bit erroneo es bit 0.
// assign data8[6] = &{~sindrome[0], ~sindrome[1],  sindrome[2]};     // Valor si el bit erroneo es bit 1.
// assign data8[5] = &{~sindrome[0], sindrome[1], ~sindrome[2]};      // Valor si el bit erroneo es bit 2.
// assign data8[4] = &{~sindrome[0], sindrome[1],  sindrome[2]};      // Valor si el bit erroneo es bit 3.
// assign data8[3] = &{sindrome[0], ~sindrome[1], ~sindrome[2]};      // Valor si el bit erroneo es bit 4.
// assign data8[2] = &{sindrome[0], ~sindrome[1],  sindrome[2]};      // Valor si el bit erroneo es bit 5.
// assign data8[1] = &{sindrome[0],  sindrome[1], ~sindrome[2]};      // Valor si el bit erroneo es bit 6.
// assign data8[0] = &{sindrome[0],  sindrome[1],  sindrome[2]};      // Valor si el bit erroneo no existe. 

// // Calculo de data.                                                 
// assign data  = datos_recibidos ^ data8[7:1];                   // Funcion XOR para cambiar el bit erroneo a su real valor.           
// // Data es los primeros 7 bits de derecha a izquierda de data8 ya que data8 es de 8 bits.

assign data = (sindrome == 3'b000) ? datos_recibidos : //No hay error 
              (sindrome == 3'b001) ? {datos_recibidos[6:1], ~datos_recibidos[0]} : //Error en bit 0
              (sindrome == 3'b010) ? {datos_recibidos[6:2], ~datos_recibidos[1], datos_recibidos[0]} : //Error en bit 1
              (sindrome == 3'b011) ? {datos_recibidos[6:3], ~datos_recibidos[2], datos_recibidos[1:0]} : //Error en bit 2
              (sindrome == 3'b100) ? {datos_recibidos[6:4], ~datos_recibidos[3], datos_recibidos[2:0]} : //Error en bit 3
              (sindrome == 3'b101) ? {datos_recibidos[6:5], ~datos_recibidos[4], datos_recibidos[3:0]} : //Error en bit 4
              (sindrome == 3'b110) ? {~datos_recibidos[6], datos_recibidos[5:0]} : //Error en bit 5
              (sindrome == 3'b111) ? {~datos_recibidos[6],datos_recibidos[5:0]} : //Error en bit 6
              7'bxxxxxxxx;
endmodule

src/design/module_detector_error.sv
module module_detector_error( // Modulo detector de error de una palabra de 7 bits.
    input  logic [6:0] datos_recibidos,  //Entrada de 7 bits [i3,i2,i1,c2,i0,c1,c0]
    output logic [2:0] sindrome,         // Salida de 3 bits [p2,p1,p0]. Síndrome de error 
    output logic       bit_error        // Salida del bit del error.
);
// Calculo del síndrome del error en la palabra recibida.
assign sindrome[0] = datos_recibidos[0]^datos_recibidos[2]^datos_recibidos[4]^datos_recibidos[6]; // p0 = c0^i0^i1^i3
assign sindrome[1] = datos_recibidos[1]^datos_recibidos[2]^datos_recibidos[5]^datos_recibidos[6]; // p1 = c1^i0^i2^i3
assign sindrome[2] = datos_recibidos[3]^datos_recibidos[4]^datos_recibidos[5]^datos_recibidos[6]; // p2 = c2^i1^i2^i3
// Se trabaja con la función XOR para calcular los bits de paridad.

assign bit_error = sindrome[0] | sindrome[1] | sindrome[2]; 
// Se trabaja con la funcion OR para encontrar el bit erroneo.
endmodule

src/design/module_7segmentos.sv
module module_7segmentos(
    input  logic[3:0] data,            // Entrada de 4 bits [d3,d2,d1,d0]. 
    output logic[6:0] display          // Salida de 7 bits [a,b,c,d,e,f,g]. 
);
// Decodificador 4 a 7 de 7bits.        abc defg    // Valores para guardar el valor de cada segmento.
assign display = (data == 4'b0000) ? 7'b111_1110:
                 (data == 4'b0001) ? 7'b011_0000:
                 (data == 4'b0010) ? 7'b110_1101:
                 (data == 4'b0011) ? 7'b111_1001:
                 (data == 4'b0100) ? 7'b011_0011:
                 (data == 4'b0101) ? 7'b101_1011:
                 (data == 4'b0110) ? 7'b101_1111:
                 (data == 4'b0111) ? 7'b111_0000:
                 (data == 4'b1000) ? 7'b111_1111:
                 (data == 4'b1001) ? 7'b111_0011:
                 7'bxxx_xxxx; // Default case, all segments off
endmodule

src/design/module_codificador.sv
module module_codificador (input logic [3:0] datos_in, //Entrada de 4 bits [3,2,1,0]
                           output logic [6:0] datos_cod); //Salida de 7 bits [7,6,5,4,3,2,1,0]

assign datos_cod[2] = datos_in[0]; // i0
assign datos_cod[4] = datos_in[1]; // i1
assign datos_cod[5] = datos_in[2]; // i2
assign datos_cod[6] = datos_in[3]; // i3

// bits de paridad
assign datos_cod[0] = datos_in[0]^datos_in[1]^datos_in[3]; // c0 cubre la paridad de los bits 1,2,4 
assign datos_cod[1] = datos_in[0]^datos_in[2]^datos_in[3]; // c1 cubre la paridad de los bits 1,3,4
assign datos_cod[3] = datos_in[1]^datos_in[2]^datos_in[3]; // c2 cubre la paridad de los bits 2,3,4
// Se trabaja con la función XOR para calcular los bits de paridad.
endmodule

src/design/module_top.sv
module module_top (
input logic [3:0] entrada,
input logic [6:0] palabra,
output logic [6:0] siete_seg,
output logic [3:0] led_o,
output logic [6:0] error
);

// Definición de las señales internas
logic [6:0] codificador_out;
logic [6:0] decodificador_in;
logic [2:0] sindrome_c;
logic [2:0] sindrome_d;
logic bit_error_c;
logic bit_error_d;
logic [6:0] palabra_out;

//señales de salida para los led y el display 7 segmentos
logic [3:0] led_cod;
logic [3:0] siete_seg_cod;

// Instancia de los módulos
module_codificador codificador (entrada,codificador_out); // codificador(.sat)
module_detector_error detector_cod(codificador_out,sindrome_c,bit_error_d);
module_corrector_error corrector_cod(sindrome_c,codificador_out,palabra_out);
module_decodificador deco_led(palabra_out,siete_seg_cod);
module_7segmentos display_cod(siete_seg_cod,siete_seg);
module_detector_error detector_deco(palabra,sindrome_d,bit_error_c);
module_corrector_error corrector_deco(sindrome_d,palabra,decodificador_in);
module_decodificador deco_display(decodificador_in,led_cod);
module_led leds(led_cod,led_o);
module_errordisp error_display(bit_error_c,error);

endmodule

src/sim/module_top_tb.sv
`timescale 1ns/1ns

module module_top_tb;

reg [3:0] entrada_tb;
reg [6:0] palabra_tb;
wire [6:0] siete_seg_tb;
wire [3:0] led_o_tb;
wire [6:0] error_tb;

// Instancia del módulo a probar
module_top dut(
    .entrada(entrada_tb),
    .palabra(palabra_tb),
    .siete_seg(siete_seg_tb),
    .led_o(led_o_tb),
    .error(error_tb)
);

// Inicialización de las señales de entrada
initial begin
    // Inicializar las señales de entrada
    entrada_tb = 4'b0000;
    palabra_tb = 7'b0000000;
    $monitor("Tiempo: %0t | Entrada: %b | Palabra: %b | Siete Segmentos: %b | LED: %b | Error: %b", $time, entrada_tb, palabra_tb, siete_seg_tb, led_o_tb, error_tb);
    // Aplicar estímulos al módulo DUT
    #50 entrada_tb = 4'b0001; palabra_tb = 7'b0000111; // Test case 1
    #50 entrada_tb = 4'b0010; palabra_tb = 7'b0010001; // Test case 2
    #50 entrada_tb = 4'b0011; palabra_tb = 7'b0010110; // Test case 3
    #50 entrada_tb = 4'b0100; palabra_tb = 7'b0101010; // Test case 4
    #50 entrada_tb = 4'b0101; palabra_tb = 7'b0101100; // Test case 5
    #50 entrada_tb = 4'b0110; palabra_tb = 7'b1011011; // Test case 6
    #50 entrada_tb = 4'b0111; palabra_tb = 7'b0110100; // Test case 7
    #50 entrada_tb = 4'b1000; palabra_tb = 7'b0001011; // Test case 8
    #50 entrada_tb = 4'b1001; palabra_tb = 7'b1111111; // Test case 9
    
    // Finalizar la simulación después de un tiempo determinado
    #100 $finish;
end
initial begin
    $dumpfile("module_top_tb.vcd");
    $dumpvars(0, module_top_tb);
end

endmodule

src/build/module_top_tb.vcd
$date
	Thu Apr 03 19:59:36 2025
$end
$version
	Icarus Verilog
$end
$timescale
	1ns
$end
$scope module module_top_tb $end
$var wire 7 ! siete_seg_tb [6:0] $end
$var wire 4 " led_o_tb [3:0] $end
$var wire 7 # error_tb [6:0] $end
$var reg 4 $ entrada_tb [3:0] $end
$var reg 7 % palabra_tb [6:0] $end
$scope module dut $end
$var wire 4 & entrada [3:0] $end
$var wire 7 ' palabra [6:0] $end
$var wire 3 ( sindrome_d [2:0] $end
$var wire 3 ) sindrome_c [2:0] $end
$var wire 4 * siete_seg_cod [3:0] $end
$var wire 7 + siete_seg [6:0] $end
$var wire 7 , palabra_out [6:0] $end
$var wire 4 - led_o [3:0] $end
$var wire 4 . led_cod [3:0] $end
$var wire 7 / error [6:0] $end
$var wire 7 0 decodificador_in [6:0] $end
$var wire 7 1 codificador_out [6:0] $end
$var wire 1 2 bit_error_d $end
$var wire 1 3 bit_error_c $end
$scope module codificador $end
$var wire 4 4 datos_in [3:0] $end
$var wire 7 5 datos_cod [6:0] $end
$upscope $end
$scope module corrector_cod $end
$var wire 7 6 datos_recibidos [6:0] $end
$var wire 3 7 sindrome [2:0] $end
$var wire 7 8 data [6:0] $end
$upscope $end
$scope module corrector_deco $end
$var wire 7 9 datos_recibidos [6:0] $end
$var wire 3 : sindrome [2:0] $end
$var wire 7 ; data [6:0] $end
$upscope $end
$scope module deco_display $end
$var wire 7 < datos_cod [6:0] $end
$var wire 4 = datos_out [3:0] $end
$upscope $end
$scope module deco_led $end
$var wire 7 > datos_cod [6:0] $end
$var wire 4 ? datos_out [3:0] $end
$upscope $end
$scope module detector_cod $end
$var wire 1 2 bit_error $end
$var wire 7 @ datos_recibidos [6:0] $end
$var wire 3 A sindrome [2:0] $end
$upscope $end
$scope module detector_deco $end
$var wire 1 3 bit_error $end
$var wire 7 B datos_recibidos [6:0] $end
$var wire 3 C sindrome [2:0] $end
$upscope $end
$scope module display_cod $end
$var wire 4 D data [3:0] $end
$var wire 7 E display [6:0] $end
$upscope $end
$scope module error_display $end
$var wire 1 3 bit_error $end
$var wire 7 F disp_error [6:0] $end
$upscope $end
$scope module leds $end
$var wire 4 G in [3:0] $end
$var wire 4 H out [3:0] $end
$upscope $end
$upscope $end
$upscope $end
$enddefinitions $end
$comment Show the parameter values. $end
$dumpall
$end
#0
$dumpvars
b1111 H
b0 G
b1111110 F
b1111110 E
b0 D
b0 C
b0 B
b0 A
b0 @
b0 ?
b0 >
b0 =
b0 <
b0 ;
b0 :
b0 9
b0 8
b0 7
b0 6
b0 5
b0 4
03
02
b0 1
b0 0
b1111110 /
b0 .
b1111 -
b0 ,
b1111110 +
b0 *
b0 )
b0 (
b0 '
b0 &
b0 %
b0 $
b1111110 #
b1111 "
b1111110 !
$end
#50
02
b0 )
b0 7
b0 A
b1110 "
b1110 -
b1110 H
b110000 !
b110000 +
b110000 E
b1 *
b1 ?
b1 D
b1 .
b1 =
b1 G
b111 ,
b111 8
b111 >
b111 0
b111 ;
b111 <
b111 1
b111 5
b111 6
b111 @
b111 %
b111 '
b111 9
b111 B
b1 $
b1 &
b1 4
#100
b110000 #
b110000 /
b110000 F
02
13
b1101101 !
b1101101 +
b1101101 E
b1101 "
b1101 -
b1101 H
b0 )
b0 7
b0 A
b100 (
b100 :
b100 C
b10 *
b10 ?
b10 D
b10 .
b10 =
b10 G
b11001 ,
b11001 8
b11001 >
b11001 0
b11001 ;
b11001 <
b11001 1
b11001 5
b11001 6
b11001 @
b10001 %
b10001 '
b10001 9
b10001 B
b10 $
b10 &
b10 4
#150
b1100 "
b1100 -
b1100 H
02
b11 .
b11 =
b11 G
b11110 0
b11110 ;
b11110 <
b1111001 !
b1111001 +
b1111001 E
b0 )
b0 7
b0 A
b11 *
b11 ?
b11 D
b11110 ,
b11110 8
b11110 >
b11110 1
b11110 5
b11110 6
b11110 @
b10110 %
b10110 '
b10110 9
b10110 B
b11 $
b11 &
b11 4
#200
b1011 "
b1011 -
b1011 H
b1111110 #
b1111110 /
b1111110 F
b110011 !
b110011 +
b110011 E
b100 .
b100 =
b100 G
02
b101010 0
b101010 ;
b101010 <
03
b0 )
b0 7
b0 A
b0 (
b0 :
b0 C
b100 *
b100 ?
b100 D
b101010 ,
b101010 8
b101010 >
b101010 1
b101010 5
b101010 6
b101010 @
b101010 %
b101010 '
b101010 9
b101010 B
b100 $
b100 &
b100 4
#250
b110000 #
b110000 /
b110000 F
02
b1011011 !
b1011011 +
b1011011 E
13
b0 )
b0 7
b0 A
b1010 "
b1010 -
b1010 H
b1 (
b1 :
b1 C
b101 *
b101 ?
b101 D
b101 .
b101 =
b101 G
b101101 ,
b101101 8
b101101 >
b101101 0
b101101 ;
b101101 <
b101101 1
b101101 5
b101101 6
b101101 @
b101100 %
b101100 '
b101100 9
b101100 B
b101 $
b101 &
b101 4
#300
b1011111 !
b1011111 +
b1011111 E
02
b111 "
b111 -
b111 H
b1000 .
b1000 =
b1000 G
b0 )
b0 7
b0 A
b1001011 0
b1001011 ;
b1001011 <
b110 *
b110 ?
b110 D
b101 (
b101 :
b101 C
b110011 ,
b110011 8
b110011 >
b110011 1
b110011 5
b110011 6
b110011 @
b1011011 %
b1011011 '
b1011011 9
b1011011 B
b110 $
b110 &
b110 4
#350
b1111110 #
b1111110 /
b1111110 F
b1000 "
b1000 -
b1000 H
02
b1110000 !
b1110000 +
b1110000 E
03
b111 .
b111 =
b111 G
b110100 0
b110100 ;
b110100 <
b0 )
b0 7
b0 A
b111 *
b111 ?
b111 D
b0 (
b0 :
b0 C
b110100 ,
b110100 8
b110100 >
b110100 1
b110100 5
b110100 6
b110100 @
b110100 %
b110100 '
b110100 9
b110100 B
b111 $
b111 &
b111 4
#400
b110000 #
b110000 /
b110000 F
b1111111 !
b1111111 +
b1111111 E
13
02
b111 "
b111 -
b111 H
b111 (
b111 :
b111 C
b1000 *
b1000 ?
b1000 D
b0 )
b0 7
b0 A
b1000 .
b1000 =
b1000 G
b1001011 ,
b1001011 8
b1001011 >
b1001011 0
b1001011 ;
b1001011 <
b1001011 1
b1001011 5
b1001011 6
b1001011 @
b1011 %
b1011 '
b1011 9
b1011 B
b1000 $
b1000 &
b1000 4
#450
b1111110 #
b1111110 /
b1111110 F
b0 "
b0 -
b0 H
02
b1110011 !
b1110011 +
b1110011 E
03
b1111 .
b1111 =
b1111 G
b1111111 0
b1111111 ;
b1111111 <
b0 )
b0 7
b0 A
b1001 *
b1001 ?
b1001 D
b0 (
b0 :
b0 C
b1001100 ,
b1001100 8
b1001100 >
b1001100 1
b1001100 5
b1001100 6
b1001100 @
b1111111 %
b1111111 '
b1111111 9
b1111111 B
b1001 $
b1001 &
b1001 4
