src/design/module_codificador.sv
module module_codificador (input logic [3:0] datos_in, //Entrada de 4 bits [3,2,1,0]
                           output logic [6:0] datos_cod); //Salida de 7 bits [7,6,5,4,3,2,1,0]

assign datos_cod[2] = datos_in[0]; // i0
assign datos_cod[4] = datos_in[1]; // i1
assign datos_cod[5] = datos_in[2]; // i2
assign datos_cod[6] = datos_in[3]; // i3

// bits de paridad
assign datos_cod[0] = datos_in[0]^datos_in[1]^datos_in[3]; // c0 cubre la paridad de los bits 1,2,4 
assign datos_cod[1] = datos_in[0]^datos_in[2]^datos_in[3]; // c1 cubre la paridad de los bits 1,3,4
assign datos_cod[3] = datos_in[1]^datos_in[2]^datos_in[3]; // c2 cubre la paridad de los bits 2,3,4
// Se trabaja con la función XOR para calcular los bits de paridad.
endmodule

src/sim/module_codificador_tb.sv
`timescale 1ns/1ns

module module_codificador_tb;

    reg  [3:0] datos_in;    // Entrada de 4 bits
    wire [6:0] datos_cod;    // Salida codificada de 7 bits

    // Instanciamos el módulo del codificador
    module_codificador dut (.datos_in(datos_in),.datos_cod(datos_cod));

    initial begin
        // Cabecera para imprimir resultados
        $display("Tiempo | Entrada | Codificado (7 bits)");
        $display("-------|--------|------------------");

        // Prueba con diferentes valores de entrada
        datos_in = 4'b0000; #10;
        $display("%t  |  %b  |   %b", $time, datos_in, datos_cod);

        datos_in = 4'b0001; #10;
        $display("%t  |  %b  |   %b", $time, datos_in, datos_cod);

        datos_in = 4'b0010; #10;
        $display("%t  |  %b  |   %b", $time, datos_in, datos_cod);

        datos_in = 4'b0011; #10;
        $display("%t  |  %b  |   %b", $time, datos_in, datos_cod);

        datos_in = 4'b0100; #10;
        $display("%t  |  %b  |   %b", $time, datos_in, datos_cod);

        datos_in = 4'b0101; #10;
        $display("%t  |  %b  |   %b", $time, datos_in, datos_cod);

        datos_in = 4'b0110; #10;
        $display("%t  |  %b  |   %b", $time, datos_in, datos_cod);

        datos_in = 4'b0111; #10;
        $display("%t  |  %b  |   %b", $time, datos_in, datos_cod);

        datos_in = 4'b1000; #10;
        $display("%t  |  %b  |   %b", $time, datos_in, datos_cod);

        datos_in = 4'b1001; #10;
        $display("%t  |  %b  |   %b", $time, datos_in, datos_cod);

        datos_in = 4'b1010; #10;
        $display("%t  |  %b  |   %b", $time, datos_in, datos_cod);

        datos_in = 4'b1011; #10;
        $display("%t  |  %b  |   %b", $time, datos_in, datos_cod);

        datos_in = 4'b1100; #10;
        $display("%t  |  %b  |   %b", $time, datos_in, datos_cod);

        datos_in = 4'b1101; #10;
        $display("%t  |  %b  |   %b", $time, datos_in, datos_cod);

        datos_in = 4'b1110; #10;
        $display("%t  |  %b  |   %b", $time, datos_in, datos_cod);

        datos_in = 4'b1111; #10;
        $display("%t  |  %b  |   %b", $time, datos_in, datos_cod);

        #10;
        $finish; // Finaliza la simulación
    end

    initial begin
        $dumpfile("module_codificador_tb.vcd");
        $dumpvars(0, module_codificador_tb);
    end

endmodule

src/build/module_codificador_tb.vcd
$date
	Fri Apr 04 23:17:39 2025
$end
$version
	Icarus Verilog
$end
$timescale
	1ns
$end
$scope module module_codificador_tb $end
$var wire 7 ! datos_cod [6:0] $end
$var reg 4 " datos_in [3:0] $end
$scope module dut $end
$var wire 4 # datos_in [3:0] $end
$var wire 7 $ datos_cod [6:0] $end
$upscope $end
$upscope $end
$enddefinitions $end
$comment Show the parameter values. $end
$dumpall
$end
#0
$dumpvars
b0 $
b0 #
b0 "
b0 !
$end
#10
b111 !
b111 $
b1 "
b1 #
#20
b11001 !
b11001 $
b10 "
b10 #
#30
b11110 !
b11110 $
b11 "
b11 #
#40
b101010 !
b101010 $
b100 "
b100 #
#50
b101101 !
b101101 $
b101 "
b101 #
#60
b110011 !
b110011 $
b110 "
b110 #
#70
b110100 !
b110100 $
b111 "
b111 #
#80
b1001011 !
b1001011 $
b1000 "
b1000 #
#90
b1001100 !
b1001100 $
b1001 "
b1001 #
#100
b1010010 !
b1010010 $
b1010 "
b1010 #
#110
b1010101 !
b1010101 $
b1011 "
b1011 #
#120
b1100001 !
b1100001 $
b1100 "
b1100 #
#130
b1100110 !
b1100110 $
b1101 "
b1101 #
#140
b1111000 !
b1111000 $
b1110 "
b1110 #
#150
b1111111 !
b1111111 $
b1111 "
b1111 #
