src/design/module_7segmentos.sv
module module_7segmentos(
    input  logic[3:0] data,            // Entrada de 4 bits [d3,d2,d1,d0]. 
    output logic[6:0] display          // Salida de 7 bits [a,b,c,d,e,f,g]. 
);
// Decodificador 4 a 7 de 7bits.                     // Valores para guardar el valor de cada segmento.
assign display = (data == 4'b0000) ? 7'b111_1110:
                 (data == 4'b0001) ? 7'b011_0000:
                 (data == 4'b0010) ? 7'b110_1101:
                 (data == 4'b0011) ? 7'b111_1001:
                 (data == 4'b0100) ? 7'b011_0011:
                 (data == 4'b0101) ? 7'b101_1011:
                 (data == 4'b0110) ? 7'b101_1111:
                 (data == 4'b0111) ? 7'b111_0000:
                 (data == 4'b1000) ? 7'b111_1111:
                 (data == 4'b1001) ? 7'b111_1001:
                 7'b000_0000; // Default case, all segments off
endmodule

src/sim/module_7segmentos_tb.sv
`timescale 1ns/1ns

module module_7segmentos_tb;

reg [3:0] in;
wire [6:0] out;

module_7segmentos dut (
    .data(in),
    .display(out)
);

// Generación de estímulos
    initial begin
        $display("-------|---------|--------");
        $display("Tiempo | Entrada | Salida ");
        $display("-------|---------|--------");

        $monitor("Tiempo = %t, Entrada = %b, Salida = %b", $time , in, out);
        
        in = 4'b0000; #10; // Caso 0
        in = 4'b0001; #10; // Caso 1
        in = 4'b0010; #10; // Caso 2
        in = 4'b0011; #10; // Caso 3
        in = 4'b0100; #10; // Caso 4
        in = 4'b0101; #10; // Caso 5
        in = 4'b0110; #10; // Caso 6
        in = 4'b0111; #10; // Caso 7
        in = 4'b1000; #10; // Caso 8
        in = 4'b1001; #10; // Caso 9
        in = 4'b1010; #10; // Caso A
        in = 4'b1011; #10; // Caso B
        in = 4'b1100; #10; // Caso C
        in = 4'b1101; #10; // Caso D
        in = 4'b1110; #10; // Caso E
        in = 4'b1111; #10; // Caso F

    end

     initial begin
        $dumpfile("module_7segmentos_tb.vcd");
        $dumpvars(0, module_7segmentos_tb);
    end
endmodule

src/build/module_7segmentos_tb.vcd
$date
	Wed Apr 02 12:28:51 2025
$end
$version
	Icarus Verilog
$end
$timescale
	1ns
$end
$scope module module_7segmentos_tb $end
$var wire 7 ! out [6:0] $end
$var reg 4 " in [3:0] $end
$scope module dut $end
$var wire 4 # data [3:0] $end
$var wire 7 $ display [6:0] $end
$upscope $end
$upscope $end
$enddefinitions $end
$comment Show the parameter values. $end
$dumpall
$end
#0
$dumpvars
b1111110 $
b0 #
b0 "
b1111110 !
$end
#10
b110000 !
b110000 $
b1 "
b1 #
#20
b1101101 !
b1101101 $
b10 "
b10 #
#30
b1111001 !
b1111001 $
b11 "
b11 #
#40
b110011 !
b110011 $
b100 "
b100 #
#50
b1011011 !
b1011011 $
b101 "
b101 #
#60
b1011111 !
b1011111 $
b110 "
b110 #
#70
b1110000 !
b1110000 $
b111 "
b111 #
#80
b1111111 !
b1111111 $
b1000 "
b1000 #
#90
b1111001 !
b1111001 $
b1001 "
b1001 #
#100
b0 !
b0 $
b1010 "
b1010 #
#110
b1011 "
b1011 #
#120
b1100 "
b1100 #
#130
b1101 "
b1101 #
#140
b1110 "
b1110 #
#150
b1111 "
b1111 #
